{"nodes": [{"id": "models_subscriptions_js", "label": "subscriptions.js", "file_type": "code", "source_file": "models/subscriptions.js", "source_location": "L1"}, {"id": "subscriptions_subscriptions", "label": "Subscriptions", "file_type": "code", "source_file": "models/subscriptions.js", "source_location": "L6"}, {"id": "subscriptions_subscriptions_init", "label": ".init()", "file_type": "code", "source_file": "models/subscriptions.js", "source_location": "L7"}], "edges": [{"source": "models_subscriptions_js", "target": "subscriptions_subscriptions", "relation": "contains", "confidence": "EXTRACTED", "source_file": "models/subscriptions.js", "source_location": "L6", "weight": 1.0}, {"source": "subscriptions_subscriptions", "target": "subscriptions_subscriptions_init", "relation": "method", "confidence": "EXTRACTED", "source_file": "models/subscriptions.js", "source_location": "L7", "weight": 1.0}], "raw_calls": [{"caller_nid": "subscriptions_subscriptions_init", "callee": "STRING", "source_file": "models/subscriptions.js", "source_location": "L22"}, {"caller_nid": "subscriptions_subscriptions_init", "callee": "STRING", "source_file": "models/subscriptions.js", "source_location": "L26"}, {"caller_nid": "subscriptions_subscriptions_init", "callee": "STRING", "source_file": "models/subscriptions.js", "source_location": "L32"}, {"caller_nid": "subscriptions_subscriptions_init", "callee": "STRING", "source_file": "models/subscriptions.js", "source_location": "L36"}, {"caller_nid": "subscriptions_subscriptions_init", "callee": "STRING", "source_file": "models/subscriptions.js", "source_location": "L40"}, {"caller_nid": "subscriptions_subscriptions_init", "callee": "STRING", "source_file": "models/subscriptions.js", "source_location": "L44"}, {"caller_nid": "subscriptions_subscriptions_init", "callee": "STRING", "source_file": "models/subscriptions.js", "source_location": "L48"}, {"caller_nid": "subscriptions_subscriptions_init", "callee": "STRING", "source_file": "models/subscriptions.js", "source_location": "L56"}, {"caller_nid": "subscriptions_subscriptions_init", "callee": "DOUBLE", "source_file": "models/subscriptions.js", "source_location": "L61"}, {"caller_nid": "subscriptions_subscriptions_init", "callee": "STRING", "source_file": "models/subscriptions.js", "source_location": "L65"}, {"caller_nid": "subscriptions_subscriptions_init", "callee": "STRING", "source_file": "models/subscriptions.js", "source_location": "L69"}, {"caller_nid": "subscriptions_subscriptions_init", "callee": "STRING", "source_file": "models/subscriptions.js", "source_location": "L82"}, {"caller_nid": "subscriptions_subscriptions_init", "callee": "STRING", "source_file": "models/subscriptions.js", "source_location": "L95"}, {"caller_nid": "subscriptions_subscriptions_init", "callee": "DOUBLE", "source_file": "models/subscriptions.js", "source_location": "L99"}, {"caller_nid": "subscriptions_subscriptions_init", "callee": "STRING", "source_file": "models/subscriptions.js", "source_location": "L104"}, {"caller_nid": "subscriptions_subscriptions_init", "callee": "DOUBLE", "source_file": "models/subscriptions.js", "source_location": "L108"}, {"caller_nid": "subscriptions_subscriptions_init", "callee": "STRING", "source_file": "models/subscriptions.js", "source_location": "L113"}, {"caller_nid": "subscriptions_subscriptions_init", "callee": "DOUBLE", "source_file": "models/subscriptions.js", "source_location": "L117"}]}