{"nodes": [{"id": "app_models_region_php", "label": "Region.php", "file_type": "code", "source_file": "app/Models/Region.php", "source_location": "L1"}, {"id": "region_region", "label": "Region", "file_type": "code", "source_file": "app/Models/Region.php", "source_location": "L12"}, {"id": "region_region_boot", "label": ".boot()", "file_type": "code", "source_file": "app/Models/Region.php", "source_location": "L23"}, {"id": "region_region_getcreatedatattribute", "label": ".getCreatedAtAttribute()", "file_type": "code", "source_file": "app/Models/Region.php", "source_location": "L32"}, {"id": "region_region_getupdatedatattribute", "label": ".getUpdatedAtAttribute()", "file_type": "code", "source_file": "app/Models/Region.php", "source_location": "L37"}, {"id": "region_region_getdeletedatattribute", "label": ".getDeletedAtAttribute()", "file_type": "code", "source_file": "app/Models/Region.php", "source_location": "L42"}, {"id": "region_region_subscriptionpricingplan", "label": ".subscriptionPricingPlan()", "file_type": "code", "source_file": "app/Models/Region.php", "source_location": "L47"}], "edges": [{"source": "app_models_region_php", "target": "model", "relation": "imports", "confidence": "EXTRACTED", "source_file": "app/Models/Region.php", "source_location": "L5", "weight": 1.0}, {"source": "app_models_region_php", "target": "softdeletes", "relation": "imports", "confidence": "EXTRACTED", "source_file": "app/Models/Region.php", "source_location": "L7", "weight": 1.0}, {"source": "app_models_region_php", "target": "str", "relation": "imports", "confidence": "EXTRACTED", "source_file": "app/Models/Region.php", "source_location": "L8", "weight": 1.0}, {"source": "app_models_region_php", "target": "carbon", "relation": "imports", "confidence": "EXTRACTED", "source_file": "app/Models/Region.php", "source_location": "L9", "weight": 1.0}, {"source": "app_models_region_php", "target": "auditable", "relation": "imports", "confidence": "EXTRACTED", "source_file": "app/Models/Region.php", "source_location": "L10", "weight": 1.0}, {"source": "app_models_region_php", "target": "region_region", "relation": "contains", "confidence": "EXTRACTED", "source_file": "app/Models/Region.php", "source_location": "L12", "weight": 1.0}, {"source": "region_region", "target": "region_region_boot", "relation": "method", "confidence": "EXTRACTED", "source_file": "app/Models/Region.php", "source_location": "L23", "weight": 1.0}, {"source": "region_region", "target": "region_region_getcreatedatattribute", "relation": "method", "confidence": "EXTRACTED", "source_file": "app/Models/Region.php", "source_location": "L32", "weight": 1.0}, {"source": "region_region", "target": "region_region_getupdatedatattribute", "relation": "method", "confidence": "EXTRACTED", "source_file": "app/Models/Region.php", "source_location": "L37", "weight": 1.0}, {"source": "region_region", "target": "region_region_getdeletedatattribute", "relation": "method", "confidence": "EXTRACTED", "source_file": "app/Models/Region.php", "source_location": "L42", "weight": 1.0}, {"source": "region_region", "target": "region_region_subscriptionpricingplan", "relation": "method", "confidence": "EXTRACTED", "source_file": "app/Models/Region.php", "source_location": "L47", "weight": 1.0}], "raw_calls": [{"caller_nid": "region_region_boot", "callee": "parent", "source_file": "app/Models/Region.php", "source_location": "L25"}, {"caller_nid": "region_region_boot", "callee": "static", "source_file": "app/Models/Region.php", "source_location": "L27"}, {"caller_nid": "region_region_boot", "callee": "Str", "source_file": "app/Models/Region.php", "source_location": "L28"}, {"caller_nid": "region_region_getcreatedatattribute", "callee": "format", "source_file": "app/Models/Region.php", "source_location": "L34"}, {"caller_nid": "region_region_getcreatedatattribute", "callee": "Carbon", "source_file": "app/Models/Region.php", "source_location": "L34"}, {"caller_nid": "region_region_getupdatedatattribute", "callee": "format", "source_file": "app/Models/Region.php", "source_location": "L39"}, {"caller_nid": "region_region_getupdatedatattribute", "callee": "Carbon", "source_file": "app/Models/Region.php", "source_location": "L39"}, {"caller_nid": "region_region_getdeletedatattribute", "callee": "format", "source_file": "app/Models/Region.php", "source_location": "L44"}, {"caller_nid": "region_region_getdeletedatattribute", "callee": "Carbon", "source_file": "app/Models/Region.php", "source_location": "L44"}, {"caller_nid": "region_region_subscriptionpricingplan", "callee": "hasOne", "source_file": "app/Models/Region.php", "source_location": "L49"}]}